{
"waste_items/LuzGAnL4NeAncmBNEKbV": {"name":"Plastic Bottle","category":"Recyclable","description":"Empty and rinse before recycling.","disposalGuide":"Remove cap if required. Rinse. Place in recycling bin.","keywords":["bottle","plastic","pet"],"imageAsset":"images/plastic_bottle.jpeg"},
"waste_items/bw4KLgEBbdXLglrtdQ3U": {"name":"Aluminum Can","category":"Recyclable","description":"Drink cans made from aluminum.","disposalGuide":"Rinse and recycle in metal recycling bin.","keywords":["can","aluminum","drink"],"imageAsset":"images/aluminum_can.jpeg"},
"waste_items/fAsSVtYjPIO1ojruncZz": {"name":"Old Phone","category":"E-Waste","description":"Unused or broken mobile phones.","disposalGuide":"Bring to electronic waste recycling centres.","keywords":["phone","mobile","electronics"],"imageAsset":"images/old_phone.jpeg"},
"waste_items/y6kbcuM1mWHkfTZ4S7vd": {"name":"Paper","category":"Recyclable","description":"Newspapers, magazines, and office paper.","disposalGuide":"Ensure paper is clean and dry. Flatten before recycling.","keywords":["paper","newspaper","magazine"],"imageAsset":"images/paper.jpeg"},
"waste_items/cIpDDhmqZ30bQB7cSNLQ": {"name":"Tissue Paper","category":"General Waste","description":"Used tissues and paper towels.","disposalGuide":"Dispose into general waste. Do not recycle.","keywords":["tissue","paper"],"imageAsset":"images/tissue.jpeg"},
"waste_items/X56fvVxX5C9iEgzessKT": {"name":"Glass Bottle","category":"Recyclable","description":"Glass bottles used for beverages.","disposalGuide":"Rinse and dispose at glass recycling points.","keywords":["glass","bottle"],"imageAsset":"images/glass_bottle.jpeg"},
"waste_items/1M4ngrsGAWpTES8srqZ4": {"name":"Light Bulb","category":"E-Waste","description":"Used or broken household light bulbs.","disposalGuide":"Do not throw into general waste. Dispose at e-waste points.","keywords":["bulb","light"],"imageAsset":"images/light_bulb.jpeg"},
"waste_items/a0dHCszzhyNhMlv6u3bV": {"name":"Cardboard","category":"Recyclable","description":"Boxes and packaging made of thick paperboard.","disposalGuide":"Flatten boxes before placing into recycling bin.","keywords":["cardboard","box"],"imageAsset":"images/cardboard.jpeg"},
"waste_items/gtM53H6G0cJKXeUtUEYN": {"name":"Food Waste","category":"General Waste","description":"Leftover food and organic waste.","disposalGuide":"Dispose into general waste bins. Do not recycle.","keywords":["food","organic","leftover"],"imageAsset":"images/food_waste..jpeg"},
"waste_items/1YUtxIwh5zLVLlw1mXYo": {"name":"Battery","category":"E-Waste","description":"Household batteries such as AA, AAA, and lithium batteries.","disposalGuide":"Bring to designated e-waste collection points.","keywords":["battery","aa","aaa","lithium"],"imageAsset":"images/battery.jpeg"},
"metadata": {"timestamp":"2026-02-15_17-20-25","ref":"waste_items"}
}
